Workbook

Sheet README
A1: Victor Wealth Triage Workbook v1
A3: Purpose: Structured intake and triage engine for a physician-specific financial assistant.
A4: Authority order:
A5: 1. victor_sterling_financial_project_continuation_brief.md
A6: 2. Brains/ constitutional source library
A7: 3. This workbook and all derivative tools
A9: Usage:
A10: - Fill Intake, Cash Flow, Debts, Accounts, and Insurance first.
A11: - Review Dashboard for triage metrics and red flags.
A12: - Use Action Plan for ranked next steps.
A13: - Copy the output from Victor Prompt into your AI workflow when needed.
A15: Important:
... A18: - Missing data should remain visible rather than guessed away.

Sheet Intake
A1: Intake
A2: Field | B2: Value | C2: Why it matters
A3: Client name | C3: Reference label only.
A4: Age | C4: Affects timeline, risk capacity, and retirement runway.
A5: State | C5: Tax and legal context.
A6: Filing status | C6: Tax planning and loan strategy context.
A7: Dependents | C7: Insurance need and liquidity pressure.
A8: Training stage | C8: Resident, fellow, attending, or other changes almost everything.
A9: Specialty | C9: Income trajectory and disability risk context.
A10: Expected attending income | C10: Needed for training-to-attending transition planning.
A11: Gross household income | C11: Base denominator for savings rate and planning.
A12: Monthly take-home pay | C12: Real cash-flow planning depends on take-home, not fantasy gross.
A13: Income stability | C13: Determines risk capacity and emergency-fund needs.
A14: Near-term goals | C14: Prevents generic advice.
A15: Notes | C15: Use for contract or family nuance.

Sheet Cash Flow
A1: Cash Flow
A2: Field | B2: Value | C2: Why it matters
A3: Monthly fixed expenses | C3: Housing, insurance, utilities, childcare, subscriptions.
A4: Monthly variable expenses | C4: Food, gas, discretionary spending, and irregular leakage.
A5: Monthly debt payments | C5: Required debt drag on cash flow.
A6: Monthly savings and investing | C6: Core numerator for savings rate.
A7: Cash buffer | C7: Liquid cash available now.
A8: Target emergency-fund months | B8: 6 | C8: Set a realistic liquidity target.
A9: Annual bonus or extra income | C9: Optional upside, not a planning crutch.

Sheet Debts
A1: Debts
A2: Debt type | B2: Federal loan? | C2: Balance | D2: Interest rate | E2: Minimum monthly payment | F2: PSLF eligible? | G2: Qualifying payments | H2: Status / notes

Sheet Accounts
A1: Accounts
A2: Account type | B2: Balance | C2: Employer match % | D2: Current annual contribution | E2: Annual contribution limit | F2: Notes

Sheet Insurance
A1: Insurance
A2: Field | B2: Value | C2: Why it matters
A3: Own-occupation disability in force? | C3: Future income is often the physician's largest asset.
A4: Employer disability coverage only? | C4: Group coverage may be inadequate or non-portable.
A5: Term life in force? | C5: Relevant when dependents or shared debts exist.
A6: Umbrella policy in force? | C6: Liability protection may matter as assets grow.
A7: Malpractice tail issue identified? | C7: Contract and job-change risk.
A8: Contract review completed? | C8: Bad employment terms can destroy wealth quietly.
A9: Insurance notes | C9: Coverage details, riders, or concerns.

Sheet Dashboard
A1: Dashboard
A2: Metric | B2: Value | C2: Interpretation | E2: Read This
A3: Gross household income | B3: =Intake!B11 | C3: Base income for planning. | E3: This dashboard is triage, not final advice.
A4: Annual savings | B4: =IFERROR('Cash Flow'!B6*12,0) | C4: From current monthly savings/investing. | E4: Missing data should reduce confidence, not trigger invented precision.
A5: Savings rate | B5: =IFERROR(B4/B3,"") | C5: Below 15% is weak, 15-25% is decent, 25%+ is strong. | E5: Federal student-loan choices require current official-rule verification.
A6: Monthly core spend | B6: =SUM('Cash Flow'!B3:B5) | C6: Core household cash outflow before optional nuance. | E6: Tax optimization requires live current-law review.
A7: Emergency-fund months | B7: =IFERROR('Cash Flow'!B7/B6,"") | C7: Liquidity buffer in months of core spend.
A8: Total debt | B8: =SUM(Debts!C3:C14) | C8: All listed debt balances combined.
A9: Federal student-loan balance | B9: =SUMIF(Debts!B3:B14,"Yes",Debts!C3:C14) | C9: Federal loans must be modeled before refinance talk.
A10: High-interest debt flag | B10: =IF(COUNTIFS(Debts!B3:B14,"No",Debts!D3:D14,">=0.08",Debts!A3:A14,"<>Mortgage")>0,"Yes","No") | C10: Any expensive non-federal debt is a triage problem.
A11: Employer match available | B11: =IF(COUNTIF(Accounts!C3:C14,">0")>0,"Yes","No") | C11: Free match should be captured before cleverness.
A12: Disability protection gap | B12: =IF(AND(OR(Intake!B8="Resident",Intake!B8="Fellow",Intake!B8="Attending",Intake!B8="Private practice"),Insurance!B3<>"Yes"),"Review now","Looks covered or unknown") | C12: Physician income needs explicit protection.
A13: Preliminary risk capacity | B13: =IF(OR(B7<3,Intake!B13="Unstable / at risk",B10="Yes"),"Constrained",IF(AND(B7>=6,OR(Intake!B13="Very stable",Intake!B13="Mostly stable"),B10="No"),"Moderate-to-High","Moderate")) | C13: Use the lower of risk capacity and risk tolerance in real planning.
A14: Missing core inputs | B14: =COUNTBLANK(Intake!B4:B14)+COUNTBLANK('Cash Flow'!B3:B8) | C14: Higher missingness means lower confidence in the plan.

Sheet Action Plan
A1: Action Plan
A2: Priority | B2: Category | C2: Victor verdict | D2: Reason | E2: Immediate next step
A3: 1 | B3: Liquidity | C3: =IF(Dashboard!B7<1,"Critical: liquidity is dangerously thin",IF(Dashboard!B7<3,"Weak: build cash before optimization","Acceptable for now")) | D3: Victor protects against ruin first. | E3: =IF(Dashboard!B7<3,"Build starter cash reserve and stop optional complexity","Maintain or continue toward target reserve")
A4: 2 | B4: High-interest debt | C4: =IF(Dashboard!B10="Yes","Attack this now","No obvious high-interest debt emergency detected") | D4: Guaranteed interest avoidance usually beats speculative expected return. | E4: =IF(Dashboard!B10="Yes","Direct surplus cash toward expensive debt payoff","Proceed to next priority")
A5: 3 | B5: Disability insurance | C5: =IF(Dashboard!B12="Review now","Protection gap identified","No immediate gap detected or details missing") | D5: For physicians, future income is often the largest asset. | E5: =IF(Dashboard!B12="Review now","Get own-occupation disability quotes and review riders","Confirm coverage details and portability")
A6: 4 | B6: Employer match | C6: =IF(Dashboard!B11="Yes","Capture full available match","No match identified or data missing") | D6: Match dollars come before clever optimization. | E6: =IF(Dashboard!B11="Yes","Verify contribution rate reaches the full match threshold","Confirm whether a match exists")
A7: 5 | B7: Federal student loans | C7: =IF(Dashboard!B9>0,"Model PSLF/IDR before any refinance talk","No federal student-loan balance detected") | D7: Never casually refinance away federal options. | E7: =IF(Dashboard!B9>0,"Gather loan type, servicer, PSLF count, repayment plan, and spouse context","Proceed only after confirming loan details")
A8: 6 | B8: Tax-advantaged investing | C8: =IF(AND(Dashboard!B7>=3,Dashboard!B10="No"),"Advance once the foundation is stable","Do not optimize before stabilizing the base") | D8: Optimization should follow stability, not replace it. | E8: Review 401k/403b, HSA, IRA, and other available account space.
A9: 7 | B9: Long-term investing | C9: Default to low-cost diversified index funds once the base is structurally sound. | D9: Complexity must earn its place. | E9: Write or refine a target allocation and contribution plan.

Sheet Victor Prompt
A1: Victor Prompt
A2: Copy or adapt the text below when you want Victor to analyze the workbook.
A4: =TEXTJOIN(CHAR(10),TRUE,"You are Victor Sterling, a physician-specific financial strategist.","Use the workbook data below. Label assumptions instead of faking certainty.","","CLIENT SNAPSHOT","- Client name: "&Intake!B3,"- Age: "&Intake!B4,"- State: "&Intake!B5,"- Filing status: "&Intake!B6,"- Dependents: "&Intake!B7,"- Training stage: "&Intake!B8,"- Specialty: "&Intake!B9,"- Expected attending income: "&TEXT(Intake!B10,"$#,##0"),"- Gross household income: "&TEXT(Intake!B11,"$#,##0"),"- Monthly take-home pay: "&TEXT(Intake!B12,"$#,##0"),"- Income stability: "&Intake!B13,"- Near-term goals: "&Intake!B14,"","KEY METRICS","- Annual savings: "&TEXT(Dashboard!B4,"$#,##0"),"- Savings rate: "&TEXT(Dashboard!B5,"0.0%"),"- Monthly core spend: "&TEXT(Dashboard!B6,"$#,##0"),"- Emergency-fund months: "&TEXT(Dashboard!B7,"0.0"),"- Total debt: "&TEXT(Dashboard!B8,"$#,##0"),"- Federal student-loan balance: "&TEXT(Dashboard!B9,"$#,##0"),"- High-interest debt flag: "&Dashboard!B10,"- Employer match available: "&Dashboard!B11,"- Disability protection gap: "&Dashboard!B12,"- Preliminary risk capacity: "&Dashboard!B13,"- Missing core inputs: "&Dashboard!B14,"","TASK","Produce: executive summary, diagnosis, assumptions, risk assessment, debt strategy, insurance strategy, retirement strategy, portfolio strategy, tax notes, lifestyle-inflation controls, and action timeline.","Verify current law before making tax or student-loan recommendations.")
